setup.py
designs/__init__.py
designs/bright.py
designs/designs.py
designs/turtle_math.py
layers/__init__.py
layers/layer1.py
layers/layer2.py
layers/layer3.py
layers/layer4.py
mandalas.egg-info/PKG-INFO
mandalas.egg-info/SOURCES.txt
mandalas.egg-info/dependency_links.txt
mandalas.egg-info/requires.txt
mandalas.egg-info/top_level.txt